[{"version":"1.0","encoding":"UTF-8","name":"SVG\u4fdd\u62a4\u53c2\u6570JSON\u89e3\u6790\u6587\u4ef6","order":"1","deviceModel":"0x11","packetID":"0x22"},{"name":"TargetAddr","byteOffset":"2","length":"1","type":"Uint8"},{"name":"SourceAddr","byteOffset":"3","length":"1","type":"Uint8"},{"name":"DeviceModel","byteOffset":"4","length":"1","type":"Uint8"},{"name":"DeviceID","byteOffset":"5","length":"1","type":"Uint8"},{"name":"PacketType","byteOffset":"6","length":"1","type":"Uint8"},{"name":"VoltageGuardlevel","byteOffset":"7","length":"1","type":"Uint8"},{"name":"CurrentGuardlevel","byteOffset":"8","length":"1","type":"Uint8"},{"name":"FreqGuardlevel","byteOffset":"9","length":"1","type":"Uint8"},{"name":"DcVoltageGuardlevel","byteOffset":"10","length":"1","type":"Uint8"},{"name":"DcCurrentGuardlevel","byteOffset":"11","length":"1","type":"Uint8"},{"name":"PowerunitGuardlevel","byteOffset":"12","length":"1","type":"Uint8"},{"name":"OverVoltageK","byteOffset":"13","length":"4","type":"float"},{"name":"UnderVoltageK","byteOffset":"17","length":"4","type":"float"},{"name":"UnbalanceK","byteOffset":"21","length":"4","type":"float"},{"name":"OverCurrentK0","byteOffset":"25","length":"4","type":"float"},{"name":"OverCurrentK1","byteOffset":"29","length":"4","type":"float"},{"name":"OverCurrentK2","byteOffset":"33","length":"4","type":"float"},{"name":"OverCurrentDelay1","byteOffset":"37","length":"4","type":"float"},{"name":"OverCurrentDelay2","byteOffset":"41","length":"4","type":"float"},{"name":"UpperFreqLimit","byteOffset":"45","length":"4","type":"float"},{"name":"LowerFreqLimit","byteOffset":"49","length":"4","type":"float"},{"name":"PhaseShiftLimit","byteOffset":"53","length":"4","type":"float"},{"name":"DCOverVoltageK0","byteOffset":"57","length":"4","type":"float"},{"name":"DCOverVoltageK1","byteOffset":"61","length":"4","type":"float"},{"name":"DCUnderVoltageK","byteOffset":"65","length":"4","type":"float"},{"name":"DCUnbalanceK","byteOffset":"69","length":"4","type":"float"},{"name":"DCOverCurrentK0","byteOffset":"73","length":"4","type":"float"},{"name":"DCOverCurrentK1","byteOffset":"77","length":"4","type":"float"},{"name":"DCOverCurrentK2","byteOffset":"81","length":"4","type":"float"},{"name":"DCOverCurrentDelay1","byteOffset":"85","length":"4","type":"float"},{"name":"DCOverCurrentDelay2","byteOffset":"89","length":"4","type":"float"},{"name":"TemperatureLimit0","byteOffset":"93","length":"4","type":"float"},{"name":"TemperatureLimit1","byteOffset":"97","length":"4","type":"float"},{"name":"Year","byteOffset":"101","length":"2","type":"Uint16"},{"name":"Month","byteOffset":"103","length":"1","type":"Uint8"},{"name":"Day","byteOffset":"104","length":"1","type":"Uint8"},{"name":"Hour","byteOffset":"105","length":"1","type":"Uint8"},{"name":"Minute","byteOffset":"106","length":"1","type":"Uint8"},{"name":"Second","byteOffset":"107","length":"1","type":"Uint8"},{"name":"CheckSum","byteOffset":"108","length":"1","type":"Uint8"}]